norecon/__init__.py
norecon/domainvalid.hy
norecon/helpers.hy
norecon/iploc.hy
norecon/noamass.hy
norecon/noffuf.hy
norecon/nofindomain.hy
norecon/nonmap.hy
norecon/norecon.hy
norecon/norecords.hy
norecon/noreport.hy
norecon/noresolvers.hy
norecon/noscreen.hy
norecon/nosubsfinder.hy
norecon/nowhois.hy
norecon/nowx.hy
norecon/project.hy
norecon/wildomains.hy
norecon/templates/domain.md
norecon/templates/ip.md
norecon/templates/record.md
norecon/templates/whois.md
norecon-0.922.dist-info/LICENSE.md
norecon-0.922.dist-info/METADATA
norecon-0.922.dist-info/WHEEL
norecon-0.922.dist-info/entry_points.txt
norecon-0.922.dist-info/top_level.txt
norecon-0.922.dist-info/RECORD
