Metadata-Version: 2.1
Name: norecon
Version: 0.922
Summary: auto recon tools for domain, whois, service scan and screenshot.
Home-page: https://github.com/ntestoc3/norecon
Author: ntestoc3
Author-email: ntoooooon@outlook.com
License: Expat
Keywords: recon hacking domain scan whois
Classifier: Development Status :: 3 - Alpha
Classifier: Intended Audience :: Developers
Classifier: License :: OSI Approved :: MIT License
Classifier: Programming Language :: Python :: 3
Classifier: Programming Language :: Python :: 3.6
Classifier: Programming Language :: Python :: 3.7
Classifier: Programming Language :: Python :: 3.8
Requires-Python: >=3.6, <4
License-File: LICENSE.md
Requires-Dist: bs4 (==0.0.1)
Requires-Dist: fake-useragent
Requires-Dist: hy (==0.20.0)
Requires-Dist: requests (==2.25.1)
Requires-Dist: retry
Requires-Dist: lxml
Requires-Dist: ratelimit
Requires-Dist: publicsuffix2
Requires-Dist: dnspython (==2.0.0)
Requires-Dist: python-whois
Requires-Dist: ipwhois (==1.2.0)
Requires-Dist: validators
Requires-Dist: event-bus
Requires-Dist: qqwry-py3
Requires-Dist: Jinja2
Requires-Dist: sqlite-utils
